{
	"configurations" : 
	[
		{
			"directories" : 
			[
				{
					"build" : ".",
					"jsonFile" : "directory-.-Debug-f5ebdc15457944623624.json",
					"minimumCMakeVersion" : 
					{
						"string" : "3.26"
					},
					"projectIndex" : 0,
					"source" : ".",
					"targetIndexes" : 
					[
						0
					]
				}
			],
			"name" : "Debug",
			"projects" : 
			[
				{
					"directoryIndexes" : 
					[
						0
					],
					"name" : "TrabalhoFinalED",
					"targetIndexes" : 
					[
						0
					]
				}
			],
			"targets" : 
			[
				{
					"directoryIndex" : 0,
					"id" : "TrabalhoFinalED::@6890427a1f51a3e7e1df",
					"jsonFile" : "target-TrabalhoFinalED-Debug-c0b47d8fcbdb46bb8728.json",
					"name" : "TrabalhoFinalED",
					"projectIndex" : 0
				}
			]
		}
	],
	"kind" : "codemodel",
	"paths" : 
	{
		"build" : "/Users/yagosouza/Developer/Faculdade/estrutura de dados/projetoFinal/ProjetoFinalEstruturaDeDados/cmake-build-debug",
		"source" : "/Users/yagosouza/Developer/Faculdade/estrutura de dados/projetoFinal/ProjetoFinalEstruturaDeDados"
	},
	"version" : 
	{
		"major" : 2,
		"minor" : 7
	}
}
